[1,["ecpdLyjvZBwrvm+cedCcQy","b8k9zBOGFPWJB7ELscYQxy","25o3kcbNRHSrsXfSy5BS7Z","ebPQ1ftL1OJpTVeetA9pEp","a2MjXRFdtLlYQ5ouAFv/+R","ddECamN9tIyJ4amtGvBfxq","2a9VVfuxxA/Jh3affCg9zq","0bMvVi1nVDQaZ8Fh0R2EFH","e4XcFzS1tIHoGT0qWbb8XS","4cHLxq+u1AwZbXFTJN98yQ","9ciZFevQBCbYFYH6p89jos","48nEOJxHdB8qJvScNVWHNd","23fUONBWJPqpEXYBvEh50l","37OiZsfN5NGKqnOJWR2TMH","25I2Af8NtPh48oWX2JoE0R","4eLEvbRONJbLbAQXABo06T","02TDPjXgFLUYJv8A8O5hcG","7cQ9sMtJpJ55+tth5cagJ7","51t0sHKBdHdK6TPxC7xbNc","428hRK04FBHqJINu/diT7W","a1+/ipOH1NlIQha6Exzfjw","c97xVLa6RODrtYjrdCAaX8","16IRWNt/9Cm54b6FCh+Qm3","86VDDC2K5Glqy0i4f6olLO","38MSGO1+ZO3ZpQorJGO/qa","12mjaYP6RG9YhoYlBO/MAs","f3s6iDTSlIj4COwzSOiX9U","c6Nb14W9JLlLuJLpwY/RSS","f70n1KXtZPVrMwC7Xzb1k2","d064+3VVNKBZYho665XFs+","accILgJ65Oq6XI03Zsx776","27lhkHDgdDpZ3j0OW1LWoM","a9xJGkIpNDWLDm/WLoyy/w","24OsF17VNBh6Z5+bp8fxQR","f1s5LhO/9Js5lUs+X6qV7m","c28+D2GfpOgq1o01qOnTAb","ddYE4LKYxBk6awCnqoA1Ra","ffDpHHVcZAhqOfy25Fe4w7","79HB53NklF0JFRHsuUg1x1","ca/Z2fYMtI5rRNFfGDhyGa","02delMVqdBD70a/HSD99FK","d0kfikWt1D5qjCeSoWiNjF","ceWCxBJLRO0pC4Ok8bGH9O","b3BFHtl0FAvLtfoTGkbu+U","02MQxtVcJDZoNNfcePldai","61Qid92Q1CSrSCNQmZrm6f","1bURxuyrJEEoIfQeETb5Kr","f7ujd0JnlIKolhhkbHLY1r","45cYAhtktNBIH2YjUnFb8S","d41chQwAFNTYphsH7Mymz2","6d3tStHm1ANZ7JrPBX5kwy","91up+nYR9HnJOKzDgtYLD7","ed0hW5J5ZKBar1gflskoHO"],["node","_spriteFrame","_textureSetter","_N$target","_parent","_defaultClip","chartsPage","PromoPage","phbNode","contentLayout","userInfo","soundBtn","tipNode","_N$background","_N$placeholderLabel","_N$textLabel","scene","_clip"],["cc.SpriteFrame",["cc.Node",["_name","_active","_id","_objFlags","_opacity","_components","_contentSize","_parent","_trs","_children","_color","_anchorPoint"],-2,9,5,1,7,2,5,5],["cc.Widget",["_alignFlags","_right","_top","_left","_originalHeight","_bottom","_originalWidth","alignMode","_verticalCenter","_horizontalCenter","node"],-7,1],["cc.Label",["_N$verticalAlign","_string","_fontSize","_N$overflow","_lineHeight","_N$horizontalAlign","_styleFlags","_enableWrapText","node","_materials"],-5,1,3],["cc.Sprite",["_sizeMode","_dstBlendFactor","_enabled","_type","node","_materials","_spriteFrame"],-1,1,3,6],["cc.Node",["_name","_opacity","_active","_parent","_components","_contentSize","_color","_anchorPoint","_trs"],0,1,12,5,5,5,7],["cc.LabelOutline",["_width","node","_color"],2,1,5],["cc.AudioSource",["_loop","playOnLoad","node","_clip"],1,1,6],["cc.Animation",["playOnLoad","node","_clips","_defaultClip"],2,1,3,6],["cc.Button",["_N$transition","node","clickEvents","_N$target","_N$normalColor"],2,1,9,1,5],["cc.SceneAsset",["_name","asyncLoadAssets"],1],["aebc05iEkpIa6XeWy1zw3Ot",["node","audioResList","tipNode","soundBtn","userInfo","contentLayout","phbNode","PromoPage","chartsPage"],3,1,3,1,1,1,1,1,1,1],["cc.Layout",["_resize","_N$layoutType","_N$spacingY","node","_layoutSize"],0,1,5],["cc.ClickEvent",["_componentId","handler","target"],1,1],["cc.Canvas",["_fitWidth","_fitHeight","node","_designResolution"],1,1,5],["cc.BlockInputEvents",["node"],3,1],["cc.EditBox",["maxLength","_N$inputMode","node","_N$textLabel","_N$placeholderLabel","_N$background"],1,1,1,1,1],["cc.ScrollView",["horizontal","node","_N$content"],2,1,1],["cc.Mask",["node","_materials"],3,1,3],["cc.Scene",["_name","_children","_anchorPoint","_trs"],2,2,5,7],["cc.Camera",["_clearFlags","_depth","node"],1,1]],[[1,0,7,5,6,8,2],[4,4,5,6,1],[1,0,7,9,5,6,8,2],[4,4,5,1],[6,0,1,2,2],[4,2,4,5,2],[13,0,1,2,3],[3,1,6,5,0,8,9,5],[1,0,1,7,5,6,8,3],[9,0,1,2,3,2],[1,0,7,5,10,6,8,2],[3,1,2,4,0,3,8,9,6],[2,0,4,10,3],[4,0,4,5,6,2],[3,1,2,4,5,0,3,8,9,7],[3,1,5,0,3,8,9,5],[1,0,7,9,8,2],[2,0,10,2],[8,0,1,2,3,2],[1,0,1,7,9,5,6,3],[1,0,7,5,6,2],[1,0,4,7,5,10,6,3],[15,0,1],[1,0,9,5,6,2],[1,0,1,7,9,5,6,8,3],[1,0,7,9,5,6,2],[2,0,1,2,10,4],[2,0,1,5,10,4],[2,7,0,3,6,4,10,6],[4,1,4,5,6,2],[9,0,1,2,4,3,2],[3,1,2,4,6,5,0,8,9,7],[6,1,2,1],[10,0,1,3],[1,0,9,5,6,11,8,2],[1,0,9,5,6,8,2],[1,0,2,9,5,6,8,3],[1,0,7,5,10,6,2],[1,0,5,6,8,2],[1,0,7,9,5,6,11,8,2],[1,0,3,7,5,6,8,3],[1,0,1,7,5,6,11,8,3],[1,0,1,7,5,10,6,3],[5,0,3,4,6,5,7,8,2],[5,0,1,3,4,6,5,3],[5,0,2,3,4,5,7,8,3],[2,0,3,1,5,10,5],[2,0,2,10,3],[2,0,3,2,10,4],[2,0,3,1,2,5,8,9,6,4,10,10],[2,7,0,6,4,10,5],[11,0,1,2,3,4,5,6,7,8,1],[7,2,1],[7,0,1,2,3,3],[12,0,1,2,3,4,4],[4,3,0,4,5,3],[8,1,1],[14,0,1,2,3,3],[16,0,1,2,3,4,5,3],[3,1,2,5,0,3,8,9,6],[3,1,2,0,3,8,9,5],[3,1,2,4,5,0,8,9,6],[3,2,4,7,0,3,8,9,6],[3,1,2,4,7,0,3,8,9,7],[6,1,1],[17,0,1,2,2],[18,0,1,1],[19,0,1,2,3,2],[20,0,1,2,3]],[[[{"name":"whhmmkftj","rect":[0,0,131,134],"offset":[0,0],"originalSize":[131,134],"capInsets":[0,0,0,0]}],[0],0,[0],[2],[11]],[[{"name":"fzwmfci","rect":[0,0,257,246],"offset":[0,0],"originalSize":[257,246],"capInsets":[0,0,0,0]}],[0],0,[0],[2],[12]],[[{"name":"snacunw","rect":[0,0,257,436],"offset":[0,0],"originalSize":[257,436],"capInsets":[0,0,0,0]}],[0],0,[0],[2],[13]],[[{"name":"sugtjzrlmf","rect":[0,0,815,658],"offset":[0,0],"originalSize":[815,658],"capInsets":[0,0,0,0]}],[0],0,[0],[2],[14]],[[{"name":"litdfmz","rect":[0,0,694,74],"offset":[0,0],"originalSize":[694,74],"capInsets":[0,0,0,0]}],[0],0,[0],[2],[15]],[[{"name":"crfpzxhdxs","rect":[0,0,223,194],"offset":[0,0],"originalSize":[223,194],"capInsets":[0,0,0,0]}],[0],0,[0],[2],[16]],[[{"name":"flmwsqblrs","rect":[0,0,377,150],"offset":[0,0],"originalSize":[377,150],"capInsets":[0,0,0,0]}],[0],0,[0],[2],[17]],[[{"name":"pfmqjn","rect":[0,0,257,242],"offset":[0,0],"originalSize":[257,242],"capInsets":[0,0,0,0]}],[0],0,[0],[2],[18]],[[{"name":"hhwxyhdpdx","rect":[0,0,223,194],"offset":[0,0],"originalSize":[223,194],"capInsets":[0,0,0,0]}],[0],0,[0],[2],[19]],[[[33,"hall",null],[23,"hallLayout",[-11,-12,-13,-14,-15,-16,-17,-18,-19],[[17,45,-1],[51,-9,[213],-8,-7,-6,-5,-4,-3,-2],[52,-10]],[5,1920,1080]],[34,"content",[-21,-22,-23,-24,-25,-26,-27,-28,-29,-30],[[54,1,2,40,-20,[5,1000,1100]]],[5,1000,1100],[0,0.5,1],[0,227.795,0,0,0,0,1,1,1,1]],[2,"contentLayout",1,[-32,-33,-34,-35,-36,-37,-38,-39,-40],[[1,-31,[67],68]],[5,1579,879],[26.224,35.602,0,0,0,0,1,1,1,1]],[24,"yjjx",false,3,[-43,-44,-45,-46,-47,-48],[[3,-41,[63]],[17,8,-42]],[5,313,822],[-633,-42.514,0,0,0,0,1,1,1,1]],[2,"userInfo",3,[-51,-52,-53,-54,-55],[[56,-49],[1,-50,[10],11]],[5,95,95],[-478.551,361.615,0,0,0,0,1,1,1,1]],[2,"icon1",3,[-59,-60,-61],[[13,2,-56,[15],16],[9,3,-58,[[6,"aebc05iEkpIa6XeWy1zw3Ot","btnEvent",1]],-57]],[5,257,436],[-497.103,33.265,0,0,0,0,1,1,1,0]],[2,"icon2",3,[-65,-66,-67],[[1,-62,[20],21],[9,3,-64,[[6,"aebc05iEkpIa6XeWy1zw3Ot","btnEvent",1]],-63]],[5,257,456],[-234.645,43.265,0,0,0,0,1,1,1,0]],[2,"icon3",3,[-71,-72,-73],[[1,-68,[25],26],[9,3,-70,[[6,"aebc05iEkpIa6XeWy1zw3Ot","btnEvent",1]],-69]],[5,257,242],[135.356,152.83,0,0,0,0,1,1,1,0]],[2,"icon4",3,[-77,-78,-79],[[1,-74,[30],31],[9,1,-76,[[6,"aebc05iEkpIa6XeWy1zw3Ot","btnEvent",1]],-75]],[5,257,246],[398.845,152.456,0,0,0,0,1,1,1,0]],[2,"icon5",3,[-83,-84,-85],[[1,-80,[35],36],[9,1,-82,[[6,"aebc05iEkpIa6XeWy1zw3Ot","btnEvent",1]],-81]],[5,257,232],[135.721,-80.697,0,0,0,0,1,1,1,0]],[2,"icon6",3,[-89,-90,-91],[[1,-86,[40],41],[9,1,-88,[[6,"aebc05iEkpIa6XeWy1zw3Ot","btnEvent",1]],-87]],[5,257,230],[398.845,-81.582,0,0,0,0,1,1,1,0]],[35,"soundBtn",[-96],[[9,3,-93,[[6,"aebc05iEkpIa6XeWy1zw3Ot","btnEvent",1]],-92],[1,-94,[76],77],[26,33,224.74300000000005,17.42,-95]],[5,131,134],[669.757,11.079999999999998,0,0,0,0,1,1,1,0]],[2,"DHM",1,[-102],[[1,-97,[82],83],[18,true,-98,[85],84],[9,1,-100,[[6,"aebc05iEkpIa6XeWy1zw3Ot","openPromo",1]],-99],[27,36,50.831999999999994,-0.5160000000000764,-101]],[5,223,194],[797.668,-443.5160000000001,0,0,0,0,1,1,1,1]],[2,"winG",1,[-108],[[1,-103,[90],91],[18,true,-104,[93],92],[9,1,-106,[[6,"aebc05iEkpIa6XeWy1zw3Ot","openCharts",1]],-105],[46,12,36.371999999999844,1660.6280000000002,-0.1610000000000582,-107]],[5,223,194],[-812.1280000000002,-443.16100000000006,0,0,0,0,1,1,1,1]],[23,"rule",[-110,-111,-112,-113,-114],[[1,-109,[114],115]],[5,815,658]],[36,"Canvas","a5esZu+45LA5mBpvttspPD",[-118,1],[[57,true,false,-115,[5,1920,1080]],[17,45,-116],[53,true,true,-117,214]],[5,1920,1080],[960,540,0,0,0,0,1,1,1,1]],[2,"topLayout",1,[-120,-121,-122,12],[[47,41,0.5,-119]],[5,1920,191],[0,444,0,0,0,0,1,1,1,1]],[19,"tipPage",false,1,[-125,-126],[[12,45,300,-123],[22,-124]],[5,1920,1080]],[19,"promoCodePage",false,1,[-129,15],[[12,45,300,-127],[22,-128]],[5,1920,1080]],[19,"chartsPage",false,1,[-132,-133],[[12,45,300,-130],[22,-131]],[5,1920,1080]],[2,"dj",2,[-135,-136,-137,-138],[[1,-134,[127],128]],[5,694,74],[0,-37,0,0,0,0,1,1,1,1]],[2,"dj",2,[-140,-141,-142,-143],[[1,-139,[136],137]],[5,694,74],[0,-151,0,0,0,0,1,1,1,1]],[2,"dj",2,[-145,-146,-147,-148],[[1,-144,[145],146]],[5,694,74],[0,-265,0,0,0,0,1,1,1,1]],[2,"dj",2,[-150,-151,-152,-153],[[1,-149,[154],155]],[5,694,74],[0,-379,0,0,0,0,1,1,1,1]],[2,"dj",2,[-155,-156,-157,-158],[[1,-154,[163],164]],[5,694,74],[0,-493,0,0,0,0,1,1,1,1]],[2,"dj",2,[-160,-161,-162,-163],[[1,-159,[172],173]],[5,694,74],[0,-607,0,0,0,0,1,1,1,1]],[2,"dj",2,[-165,-166,-167,-168],[[1,-164,[181],182]],[5,694,74],[0,-721,0,0,0,0,1,1,1,1]],[2,"dj",2,[-170,-171,-172,-173],[[1,-169,[190],191]],[5,694,74],[0,-835,0,0,0,0,1,1,1,1]],[2,"dj",2,[-175,-176,-177,-178],[[1,-174,[199],200]],[5,694,74],[0,-949,0,0,0,0,1,1,1,1]],[2,"dj",2,[-180,-181,-182,-183],[[1,-179,[208],209]],[5,694,74],[0,-1063,0,0,0,0,1,1,1,1]],[16,"userInfo",4,[-184,-185,-186,-187],[-49.209,157,0,0,0,0,1,0.9,0.9,1]],[16,"userInfo",4,[-188,-189,-190,-191],[-49.209,15,0,0,0,0,1,0.9,0.9,1]],[16,"userInfo",4,[-192,-193,-194,-195],[-49.209,-128,0,0,0,0,1,0.9,0.9,1]],[16,"userInfo",4,[-196,-197,-198,-199],[-49.209,-270,0,0,0,0,1,0.9,0.9,1]],[16,"userInfo",4,[-200,-201,-202,-203],[-49.209,-413,0,0,0,0,1,0.9,0.9,1]],[2,"btnStartGame",3,[-207],[[1,-204,[65],66],[9,3,-206,[[6,"aebc05iEkpIa6XeWy1zw3Ot","btnEvent",1]],-205]],[5,377,150],[283.811,-274.289,0,0,0,0,1,0.84,0.84,0]],[0,"backBtn",17,[[9,3,-209,[[6,"aebc05iEkpIa6XeWy1zw3Ot","btnEvent",1]],-208],[1,-210,[69],70],[26,33,27.787000000000035,16.646,-211]],[5,131,134],[866.713,11.854,0,0,0,0,1,1,1,0]],[0,"tipBtn",17,[[9,3,-213,[[6,"aebc05iEkpIa6XeWy1zw3Ot","btnEvent",1]],-212],[1,-214,[71],72],[48,9,46.16300000000001,18.227000000000004,-215]],[5,131,134],[-848.337,10.272999999999996,0,0,0,0,1,1,1,0]],[10,"DHM",13,[[29,772,-216,[78],79],[18,true,-217,[81],80],[30,1,-219,[[6,"aebc05iEkpIa6XeWy1zw3Ot","openPromo",1]],[4,4278246399],-218]],[4,4278246399],[5,223,194],[0,0,0,0,0,0,1,1,1,0]],[37,"winG",14,[[29,772,-220,[86],87],[18,true,-221,[89],88],[30,1,-223,[[6,"aebc05iEkpIa6XeWy1zw3Ot","openCharts",1]],[4,4278254799],-222]],[4,4278254799],[5,223,194]],[0,"backBtn",1,[[9,1,-225,[[6,"aebc05iEkpIa6XeWy1zw3Ot","btnEvent",1]],-224],[1,-226,[94],95],[27,36,311.94000000000005,0.09600000000000364,-227]],[5,223,194],[536.56,-442.904,0,0,0,0,1,1,1,1]],[2,"EditBox",15,[-232,-233,-234],[[58,8,6,-231,-230,-229,-228]],[5,693,104],[-1.664,-134.756,0,0,0,0,1,1,1,1]],[2,"closePromoBtn",15,[-238],[[1,-235,[112],113],[9,3,-237,[[6,"aebc05iEkpIa6XeWy1zw3Ot","btnEvent",1]],-236]],[5,377,150],[0.114,-411.436,0,0,0,0,1,1,1,0]],[10,"userID",36,[[14,"Quick match",60,60,1,1,2,-239,[64]],[4,2,-240,[4,4282754593]],[49,18,51,51,33,33,12.433,2.032,282,50,-241]],[4,4282754593],[5,282,50],[2.032,12.433,0,0,0,0,1,1,1,1]],[38,"closeTipBtn",[[1,-242,[98],99],[9,3,-244,[[6,"aebc05iEkpIa6XeWy1zw3Ot","btnEvent",1]],-243]],[5,33,33],[321.202,294.053,0,0,0,0,1,1,1,0]],[0,"closePromoBtn",15,[[1,-245,[104],105],[9,3,-247,[[6,"aebc05iEkpIa6XeWy1zw3Ot","btnEvent",1]],-246]],[5,33,33],[321.202,289.645,0,0,0,0,1,1,1,0]],[43,"PLACEHOLDER_LABEL",42,[[-248,[28,0,45,2,158,40,-249],[32,-250,[4,4282075262]]],1,4,4],[4,4292277245],[5,691,104],[0,0,1],[-344.5,52,0,0,0,0,1,1,1,1]],[25,"rule",20,[-252,-253],[[1,-251,[211],212]],[5,815,658]],[0,"closeChartsBtn",48,[[1,-254,[118],119],[9,3,-256,[[6,"aebc05iEkpIa6XeWy1zw3Ot","btnEvent",1]],-255]],[5,33,33],[322.103,294.007,0,0,0,0,1,1,1,0]],[2,"soreView",48,[2],[[65,false,-257,2],[66,-258,[210]]],[5,730,500],[0.233,-31.934,0,0,0,0,1,1,1,1]],[2,"jb",21,[-260,-261],[[5,false,-259,[125]]],[5,213,62],[192.851,2.148,0,0,0,0,1,1,1,1]],[2,"jb",22,[-263,-264],[[5,false,-262,[134]]],[5,213,62],[192.851,2.148,0,0,0,0,1,1,1,1]],[2,"jb",23,[-266,-267],[[5,false,-265,[143]]],[5,213,62],[192.851,2.148,0,0,0,0,1,1,1,1]],[2,"jb",24,[-269,-270],[[5,false,-268,[152]]],[5,213,62],[192.851,2.148,0,0,0,0,1,1,1,1]],[2,"jb",25,[-272,-273],[[5,false,-271,[161]]],[5,213,62],[192.851,2.148,0,0,0,0,1,1,1,1]],[2,"jb",26,[-275,-276],[[5,false,-274,[170]]],[5,213,62],[192.851,2.148,0,0,0,0,1,1,1,1]],[2,"jb",27,[-278,-279],[[5,false,-277,[179]]],[5,213,62],[192.851,2.148,0,0,0,0,1,1,1,1]],[2,"jb",28,[-281,-282],[[5,false,-280,[188]]],[5,213,62],[192.851,2.148,0,0,0,0,1,1,1,1]],[2,"jb",29,[-284,-285],[[5,false,-283,[197]]],[5,213,62],[192.851,2.148,0,0,0,0,1,1,1,1]],[2,"jb",30,[-287,-288],[[5,false,-286,[206]]],[5,213,62],[192.851,2.148,0,0,0,0,1,1,1,1]],[20,"bg",1,[[17,45,-289],[13,0,-290,[0],1]],[5,1920,1080]],[0,"userID",5,[[59,"ID:10086",16,1,1,2,-291,[6]],[64,-292]],[5,188,50],[119.532,11.789,0,0,0,0,1,1,1,1]],[39,"score",5,[-294],[[5,false,-293,[8]]],[5,213,62],[0,-0.1939597281958284,1.0253848213465702],[73.243,97.283,0,0,0,0,1,1,1,1]],[10,"scoreLaberl",5,[[60,"88888",19,1,2,-295,[9]],[32,-296,[4,4278836735]]],[4,4278836735],[5,214,61],[189.506,-15.053,0,0,0,0,1,1,1,1]],[8,"num",false,6,[[15,"1000",1,1,2,-297,[14]],[4,2,-298,[4,4278190080]]],[5,115.1,50],[11,-395,0,0,0,0,1,1,1,1]],[8,"num",false,7,[[15,"1000",1,1,2,-299,[19]],[4,2,-300,[4,4278190080]]],[5,115.1,50],[11,-408,0,0,0,0,1,1,1,1]],[8,"num",false,8,[[15,"1000",1,1,2,-301,[24]],[4,2,-302,[4,4278190080]]],[5,115.1,50],[29.325,-547.22,0,0,0,0,1,1,1,1]],[8,"num",false,9,[[15,"1000",1,1,2,-303,[29]],[4,2,-304,[4,4278190080]]],[5,115.1,50],[29.325,-547.22,0,0,0,0,1,1,1,1]],[8,"num",false,10,[[15,"1000",1,1,2,-305,[34]],[4,2,-306,[4,4278190080]]],[5,115.1,50],[29.325,-547.22,0,0,0,0,1,1,1,1]],[8,"num",false,11,[[15,"1000",1,1,2,-307,[39]],[4,2,-308,[4,4278190080]]],[5,115.1,50],[29.325,-547.22,0,0,0,0,1,1,1,1]],[0,"userID",31,[[11,"ID:151135",30,30,1,2,-309,[44]],[4,2,-310,[4,4278190080]]],[5,188,50],[174.985,116.217,0,0,0,0,1,1,1,1]],[0,"scoreLaberl",31,[[11,"985548",30,30,1,2,-311,[45]],[4,2,-312,[4,4278190080]]],[5,130.4,61],[154.6,71.1,0,0,0,0,1,1,1,1]],[10,"num",31,[[14,"1",50,50,1,1,2,-313,[46]],[4,2,-314,[4,4278190080]]],[4,4294909161],[5,54,76],[-90.174,96.202,0,0,0,0,1,1,1,1]],[0,"userID",32,[[11,"ID:145198",30,30,1,2,-315,[48]],[4,2,-316,[4,4278190080]]],[5,188,50],[174.985,116.217,0,0,0,0,1,1,1,1]],[0,"scoreLaberl",32,[[11,"886548",30,30,1,2,-317,[49]],[4,2,-318,[4,4278190080]]],[5,130.4,61],[154.6,71.1,0,0,0,0,1,1,1,1]],[10,"num",32,[[14,"2",50,50,1,1,2,-319,[50]],[4,2,-320,[4,4278190080]]],[4,4294909161],[5,54,76],[-90.174,96.202,0,0,0,0,1,1,1,1]],[0,"userID",33,[[11,"ID:515198",30,30,1,2,-321,[52]],[4,2,-322,[4,4278190080]]],[5,188,50],[174.985,116.217,0,0,0,0,1,1,1,1]],[0,"scoreLaberl",33,[[11,"854248",30,30,1,2,-323,[53]],[4,2,-324,[4,4278190080]]],[5,130.4,61],[154.6,71.1,0,0,0,0,1,1,1,1]],[10,"num",33,[[14,"3",50,50,1,1,2,-325,[54]],[4,2,-326,[4,4278190080]]],[4,4294909161],[5,54,76],[-90.174,96.202,0,0,0,0,1,1,1,1]],[0,"userID",34,[[11,"ID:127118",30,30,1,2,-327,[56]],[4,2,-328,[4,4278190080]]],[5,188,50],[174.985,116.217,0,0,0,0,1,1,1,1]],[0,"scoreLaberl",34,[[11,"791588",30,30,1,2,-329,[57]],[4,2,-330,[4,4278190080]]],[5,130.4,61],[154.6,71.1,0,0,0,0,1,1,1,1]],[10,"num",34,[[14,"4",50,50,1,1,2,-331,[58]],[4,2,-332,[4,4278190080]]],[4,4294909161],[5,54,76],[-90.174,96.202,0,0,0,0,1,1,1,1]],[0,"userID",35,[[11,"ID:127118",30,30,1,2,-333,[60]],[4,2,-334,[4,4278190080]]],[5,188,50],[174.985,116.217,0,0,0,0,1,1,1,1]],[0,"scoreLaberl",35,[[11,"791588",30,30,1,2,-335,[61]],[4,2,-336,[4,4278190080]]],[5,130.4,61],[154.6,71.1,0,0,0,0,1,1,1,1]],[10,"num",35,[[14,"5",50,50,1,1,2,-337,[62]],[4,2,-338,[4,4278190080]]],[4,4294909161],[5,54,76],[-90.174,96.202,0,0,0,0,1,1,1,1]],[24,"shareBtn",false,17,[-341],[[9,3,-340,[[6,"aebc05iEkpIa6XeWy1zw3Ot","btnEvent",1]],-339]],[5,125,132],[294,1.707,0,0,0,0,1,1,1,0]],[40,"back",512,86,[[3,-342,[73]]],[5,134,118],[0,0,0,0,0,0,1,1,1,0]],[21,"pageBG",127,18,[[13,0,-343,[96],97],[12,45,300,-344]],[4,4278190080],[5,1920,1080]],[25,"rule",18,[45],[[1,-345,[100],101]],[5,815,658]],[21,"pageBG",127,19,[[13,0,-346,[102],103],[12,45,300,-347]],[4,4278190080],[5,1920,1080]],[10,"title",15,[[31,"Promo Code",44,60,1,1,1,-348,[106]],[4,3,-349,[4,4282075262]]],[4,4292277245],[5,267.57,81.6],[9.412,287.285,0,0,0,0,1,1,1,1]],[44,"BACKGROUND_SPRITE",180,42,[[-350,[50,0,45,160,40,-351]],1,4],[4,4292277245],[5,693,104]],[45,"TEXT_LABEL",false,42,[[-352,[28,0,45,2,158,40,-353]],1,4],[5,691,104],[0,0,1],[-344.5,52,0,0,0,0,1,1,1,1]],[21,"pageBG",127,20,[[13,0,-354,[116],117],[12,45,300,-355]],[4,4278190080],[5,1920,1080]],[67,"New Node",[16],[0,0,0],[0,0,0,0,0,0,1,1,1,1]],[20,"Main Camera",16,[[68,7,-1,-356]],[5,1920,1080]],[41,"yjjx",false,5,[[13,2,-357,[2],3]],[5,233,75],[0,0.5064307850006834,0.5603602394123552],[101.606,1.107,0,0,0,0,1,1,1,1]],[20,"tx",5,[[1,-358,[4],5]],[5,95,95]],[8,"gold",false,63,[[3,-359,[7]]],[5,63,64],[50.229,-30.743,0,0,0,0,1,1,1,1]],[8,"r",false,6,[[3,-360,[12]]],[5,383,60],[0,-395,0,0,0,0,1,1,1,1]],[8,"peoicon",false,6,[[3,-361,[13]]],[5,62,46],[-127.101,-395.889,0,0,0,0,1,1,1,1]],[8,"r",false,7,[[3,-362,[17]]],[5,383,60],[0,-406,0,0,0,0,1,1,1,1]],[8,"peoicon",false,7,[[3,-363,[18]]],[5,62,46],[-127,-410,0,0,0,0,1,1,1,1]],[8,"r",false,8,[[3,-364,[22]]],[5,383,60],[18.753,-547.22,0,0,0,0,1,1,1,1]],[8,"peoicon",false,8,[[3,-365,[23]]],[5,62,46],[-108.348,-547.786,0,0,0,0,1,1,1,1]],[8,"r",false,9,[[3,-366,[27]]],[5,383,60],[18.753,-547.22,0,0,0,0,1,1,1,1]],[8,"peoicon",false,9,[[3,-367,[28]]],[5,62,46],[-108.348,-547.786,0,0,0,0,1,1,1,1]],[8,"r",false,10,[[3,-368,[32]]],[5,383,60],[18.753,-547.22,0,0,0,0,1,1,1,1]],[8,"peoicon",false,10,[[3,-369,[33]]],[5,62,46],[-108.348,-547.786,0,0,0,0,1,1,1,1]],[8,"r",false,11,[[3,-370,[37]]],[5,383,60],[18.753,-547.22,0,0,0,0,1,1,1,1]],[8,"peoicon",false,11,[[3,-371,[38]]],[5,62,46],[-108.348,-547.786,0,0,0,0,1,1,1,1]],[0,"Historical achievements",4,[[3,-372,[42]]],[5,224,75],[-14.397,366.207,0,0,0,0,1,1,1,1]],[0,"tx",31,[[3,-373,[43]]],[5,173,169],[0.636,106.743,0,0,0,0,1,0.8,0.8,1]],[0,"tx",32,[[3,-374,[47]]],[5,173,169],[0.636,106.743,0,0,0,0,1,0.8,0.8,1]],[0,"tx",33,[[3,-375,[51]]],[5,173,169],[0.636,106.743,0,0,0,0,1,0.8,0.8,1]],[0,"tx",34,[[3,-376,[55]]],[5,173,169],[0.636,106.743,0,0,0,0,1,0.8,0.8,1]],[0,"tx",35,[[3,-377,[59]]],[5,173,169],[0.636,106.743,0,0,0,0,1,0.8,0.8,1]],[42,"banSound",false,12,[[1,-378,[74],75]],[4,4290559164],[5,131,134]],[10,"laber",15,[[61,"lf you have a promo to claim\n\n rewards. code,pleaseenter it ",50,60,1,1,-379,[107]]],[4,4292277245],[5,655.91,195.6],[-2.243,43.497,0,0,0,0,1,1,1,1]],[55,1,0,92,[108]],[62,50,50,false,1,1,93,[109]],[63,"Enter promo code:",50,50,false,1,1,47,[110]],[10,"title",43,[[31,"Claim",60,60,1,1,1,-380,[111]]],[4,4282754593],[5,163.39,75.6],[0,8.859,0,0,0,0,1,1,1,1]],[0,"head",21,[[1,-381,[120],121]],[5,95,95],[-320.908,3.176,0,0,0,0,1,1,1,1]],[0,"New Label",21,[[7,"Michael",1,1,1,-382,[122]]],[5,146.72,50.4],[-132.609,4.88,0,0,0,0,1,1,1,1]],[0,"gold",51,[[5,false,-383,[123]]],[5,63,64],[-98.151,-1.345,0,0,0,0,1,1,1,1]],[0,"New Label",51,[[7,"867967",1,1,1,-384,[124]]],[5,133.48,50.4],[4.838,-1.547,0,0,0,0,1,1,1,1]],[0,"top1",21,[[3,-385,[126]]],[5,104,75],[492.957,44.457,0,0,0,0,1,1,1,1]],[0,"head",22,[[1,-386,[129],130]],[5,95,95],[-320.908,3.176,0,0,0,0,1,1,1,1]],[0,"New Label",22,[[7,"Emily",1,1,1,-387,[131]]],[5,106.72,50.4],[-132.609,4.88,0,0,0,0,1,1,1,1]],[0,"gold",52,[[5,false,-388,[132]]],[5,63,64],[-98.151,-1.345,0,0,0,0,1,1,1,1]],[0,"New Label",52,[[7,"1234543",1,1,1,-389,[133]]],[5,155.72,50.4],[4.838,-1.547,0,0,0,0,1,1,1,1]],[0,"top1",22,[[3,-390,[135]]],[5,104,75],[492.957,44.457,0,0,0,0,1,1,1,1]],[0,"head",23,[[1,-391,[138],139]],[5,95,95],[-320.908,3.176,0,0,0,0,1,1,1,1]],[0,"New Label",23,[[7,"David",1,1,1,-392,[140]]],[5,108.93,50.4],[-132.609,4.88,0,0,0,0,1,1,1,1]],[0,"gold",53,[[5,false,-393,[141]]],[5,63,64],[-98.151,-1.345,0,0,0,0,1,1,1,1]],[0,"New Label",53,[[7,"45345",1,1,1,-394,[142]]],[5,111.23,50.4],[4.838,-1.547,0,0,0,0,1,1,1,1]],[0,"top1",23,[[3,-395,[144]]],[5,104,75],[492.957,44.457,0,0,0,0,1,1,1,1]],[0,"head",24,[[1,-396,[147],148]],[5,95,95],[-320.908,3.176,0,0,0,0,1,1,1,1]],[0,"New Label",24,[[7,"Christopher",1,1,1,-397,[149]]],[5,226.68,50.4],[-132.609,4.88,0,0,0,0,1,1,1,1]],[0,"gold",54,[[5,false,-398,[150]]],[5,63,64],[-98.151,-1.345,0,0,0,0,1,1,1,1]],[0,"New Label",54,[[7,"243654",1,1,1,-399,[151]]],[5,133.48,50.4],[4.838,-1.547,0,0,0,0,1,1,1,1]],[0,"top1",24,[[3,-400,[153]]],[5,104,75],[492.957,44.457,0,0,0,0,1,1,1,1]],[0,"head",25,[[1,-401,[156],157]],[5,95,95],[-320.908,3.176,0,0,0,0,1,1,1,1]],[0,"New Label",25,[[7,"Olivia",1,1,1,-402,[158]]],[5,108.95,50.4],[-132.609,4.88,0,0,0,0,1,1,1,1]],[0,"gold",55,[[5,false,-403,[159]]],[5,63,64],[-98.151,-1.345,0,0,0,0,1,1,1,1]],[0,"New Label",55,[[7,"12434325",1,1,1,-404,[160]]],[5,177.97,50.4],[4.838,-1.547,0,0,0,0,1,1,1,1]],[0,"top1",25,[[3,-405,[162]]],[5,104,75],[492.957,44.457,0,0,0,0,1,1,1,1]],[0,"head",26,[[1,-406,[165],166]],[5,95,95],[-320.908,3.176,0,0,0,0,1,1,1,1]],[0,"New Label",26,[[7,"Matthew",1,1,1,-407,[167]]],[5,160,50.4],[-132.609,4.88,0,0,0,0,1,1,1,1]],[0,"gold",56,[[5,false,-408,[168]]],[5,63,64],[-98.151,-1.345,0,0,0,0,1,1,1,1]],[0,"New Label",56,[[7,"535435",1,1,1,-409,[169]]],[5,133.48,50.4],[4.838,-1.547,0,0,0,0,1,1,1,1]],[0,"top1",26,[[3,-410,[171]]],[5,104,75],[492.957,44.457,0,0,0,0,1,1,1,1]],[0,"head",27,[[1,-411,[174],175]],[5,95,95],[-320.908,3.176,0,0,0,0,1,1,1,1]],[0,"New Label",27,[[7,"Joshua",1,1,1,-412,[176]]],[5,140.04,50.4],[-132.609,4.88,0,0,0,0,1,1,1,1]],[0,"gold",57,[[5,false,-413,[177]]],[5,63,64],[-98.151,-1.345,0,0,0,0,1,1,1,1]],[0,"New Label",57,[[7,"124434",1,1,1,-414,[178]]],[5,133.48,50.4],[4.838,-1.547,0,0,0,0,1,1,1,1]],[0,"top1",27,[[3,-415,[180]]],[5,104,75],[492.957,44.457,0,0,0,0,1,1,1,1]],[0,"head",28,[[1,-416,[183],184]],[5,95,95],[-320.908,3.176,0,0,0,0,1,1,1,1]],[0,"New Label",28,[[7,"Sarah",1,1,1,-417,[185]]],[5,111.17,50.4],[-132.609,4.88,0,0,0,0,1,1,1,1]],[0,"gold",58,[[5,false,-418,[186]]],[5,63,64],[-98.151,-1.345,0,0,0,0,1,1,1,1]],[0,"New Label",58,[[7,"133453",1,1,1,-419,[187]]],[5,133.48,50.4],[4.838,-1.547,0,0,0,0,1,1,1,1]],[0,"top1",28,[[3,-420,[189]]],[5,104,75],[492.957,44.457,0,0,0,0,1,1,1,1]],[0,"head",29,[[1,-421,[192],193]],[5,95,95],[-320.908,3.176,0,0,0,0,1,1,1,1]],[0,"New Label",29,[[7,"Joseph",1,1,1,-422,[194]]],[5,140.04,50.4],[-132.609,4.88,0,0,0,0,1,1,1,1]],[0,"gold",59,[[5,false,-423,[195]]],[5,63,64],[-98.151,-1.345,0,0,0,0,1,1,1,1]],[0,"New Label",59,[[7,"46576",1,1,1,-424,[196]]],[5,111.23,50.4],[4.838,-1.547,0,0,0,0,1,1,1,1]],[0,"top1",29,[[3,-425,[198]]],[5,104,75],[492.957,44.457,0,0,0,0,1,1,1,1]],[0,"head",30,[[1,-426,[201],202]],[5,95,95],[-320.908,3.176,0,0,0,0,1,1,1,1]],[0,"New Label",30,[[7,"Rachel",1,1,1,-427,[203]]],[5,131.17,50.4],[-132.609,4.88,0,0,0,0,1,1,1,1]],[0,"gold",60,[[5,false,-428,[204]]],[5,63,64],[-98.151,-1.345,0,0,0,0,1,1,1,1]],[0,"New Label",60,[[7,"1434234",1,1,1,-429,[205]]],[5,155.72,50.4],[4.838,-1.547,0,0,0,0,1,1,1,1]],[0,"top1",30,[[3,-430,[207]]],[5,104,75],[492.957,44.457,0,0,0,0,1,1,1,1]]],0,[0,0,1,0,6,20,0,7,19,0,8,4,0,9,3,0,10,5,0,11,12,0,12,18,0,0,1,0,0,1,0,-1,61,0,-2,3,0,-3,17,0,-4,13,0,-5,14,0,-6,41,0,-7,18,0,-8,19,0,-9,20,0,0,2,0,-1,21,0,-2,22,0,-3,23,0,-4,24,0,-5,25,0,-6,26,0,-7,27,0,-8,28,0,-9,29,0,-10,30,0,0,3,0,-1,5,0,-2,6,0,-3,7,0,-4,8,0,-5,9,0,-6,10,0,-7,11,0,-8,4,0,-9,36,0,0,4,0,0,4,0,-1,112,0,-2,31,0,-3,32,0,-4,33,0,-5,34,0,-6,35,0,0,5,0,0,5,0,-1,97,0,-2,98,0,-3,62,0,-4,63,0,-5,64,0,0,6,0,3,6,0,0,6,0,-1,100,0,-2,101,0,-3,65,0,0,7,0,3,7,0,0,7,0,-1,102,0,-2,103,0,-3,66,0,0,8,0,3,8,0,0,8,0,-1,104,0,-2,105,0,-3,67,0,0,9,0,3,9,0,0,9,0,-1,106,0,-2,107,0,-3,68,0,0,10,0,3,10,0,0,10,0,-1,108,0,-2,109,0,-3,69,0,0,11,0,3,11,0,0,11,0,-1,110,0,-2,111,0,-3,70,0,3,12,0,0,12,0,0,12,0,0,12,0,-1,118,0,0,13,0,0,13,0,3,13,0,0,13,0,0,13,0,-1,39,0,0,14,0,0,14,0,3,14,0,0,14,0,0,14,0,-1,40,0,0,15,0,-1,46,0,-2,91,0,-3,119,0,-4,42,0,-5,43,0,0,16,0,0,16,0,0,16,0,-1,96,0,0,17,0,-1,37,0,-2,38,0,-3,86,0,0,18,0,0,18,0,-1,88,0,-2,89,0,0,19,0,0,19,0,-1,90,0,0,20,0,0,20,0,-1,94,0,-2,48,0,0,21,0,-1,124,0,-2,125,0,-3,51,0,-4,128,0,0,22,0,-1,129,0,-2,130,0,-3,52,0,-4,133,0,0,23,0,-1,134,0,-2,135,0,-3,53,0,-4,138,0,0,24,0,-1,139,0,-2,140,0,-3,54,0,-4,143,0,0,25,0,-1,144,0,-2,145,0,-3,55,0,-4,148,0,0,26,0,-1,149,0,-2,150,0,-3,56,0,-4,153,0,0,27,0,-1,154,0,-2,155,0,-3,57,0,-4,158,0,0,28,0,-1,159,0,-2,160,0,-3,58,0,-4,163,0,0,29,0,-1,164,0,-2,165,0,-3,59,0,-4,168,0,0,30,0,-1,169,0,-2,170,0,-3,60,0,-4,173,0,-1,113,0,-2,71,0,-3,72,0,-4,73,0,-1,114,0,-2,74,0,-3,75,0,-4,76,0,-1,115,0,-2,77,0,-3,78,0,-4,79,0,-1,116,0,-2,80,0,-3,81,0,-4,82,0,-1,117,0,-2,83,0,-3,84,0,-4,85,0,0,36,0,3,36,0,0,36,0,-1,44,0,3,37,0,0,37,0,0,37,0,0,37,0,3,38,0,0,38,0,0,38,0,0,38,0,0,39,0,0,39,0,3,39,0,0,39,0,0,40,0,0,40,0,3,40,0,0,40,0,3,41,0,0,41,0,0,41,0,0,41,0,13,120,0,14,122,0,15,121,0,0,42,0,-1,92,0,-2,93,0,-3,47,0,0,43,0,3,43,0,0,43,0,-1,123,0,0,44,0,0,44,0,0,44,0,0,45,0,3,45,0,0,45,0,0,46,0,3,46,0,0,46,0,-1,122,0,0,47,0,0,47,0,0,48,0,-1,49,0,-2,50,0,0,49,0,3,49,0,0,49,0,0,50,0,0,50,0,0,51,0,-1,126,0,-2,127,0,0,52,0,-1,131,0,-2,132,0,0,53,0,-1,136,0,-2,137,0,0,54,0,-1,141,0,-2,142,0,0,55,0,-1,146,0,-2,147,0,0,56,0,-1,151,0,-2,152,0,0,57,0,-1,156,0,-2,157,0,0,58,0,-1,161,0,-2,162,0,0,59,0,-1,166,0,-2,167,0,0,60,0,-1,171,0,-2,172,0,0,61,0,0,61,0,0,62,0,0,62,0,0,63,0,-1,99,0,0,64,0,0,64,0,0,65,0,0,65,0,0,66,0,0,66,0,0,67,0,0,67,0,0,68,0,0,68,0,0,69,0,0,69,0,0,70,0,0,70,0,0,71,0,0,71,0,0,72,0,0,72,0,0,73,0,0,73,0,0,74,0,0,74,0,0,75,0,0,75,0,0,76,0,0,76,0,0,77,0,0,77,0,0,78,0,0,78,0,0,79,0,0,79,0,0,80,0,0,80,0,0,81,0,0,81,0,0,82,0,0,82,0,0,83,0,0,83,0,0,84,0,0,84,0,0,85,0,0,85,0,3,87,0,0,86,0,-1,87,0,0,87,0,0,88,0,0,88,0,0,89,0,0,90,0,0,90,0,0,91,0,0,91,0,-1,120,0,0,92,0,-1,121,0,0,93,0,0,94,0,0,94,0,0,96,0,0,97,0,0,98,0,0,99,0,0,100,0,0,101,0,0,102,0,0,103,0,0,104,0,0,105,0,0,106,0,0,107,0,0,108,0,0,109,0,0,110,0,0,111,0,0,112,0,0,113,0,0,114,0,0,115,0,0,116,0,0,117,0,0,118,0,0,119,0,0,123,0,0,124,0,0,125,0,0,126,0,0,127,0,0,128,0,0,129,0,0,130,0,0,131,0,0,132,0,0,133,0,0,134,0,0,135,0,0,136,0,0,137,0,0,138,0,0,139,0,0,140,0,0,141,0,0,142,0,0,143,0,0,144,0,0,145,0,0,146,0,0,147,0,0,148,0,0,149,0,0,150,0,0,151,0,0,152,0,0,153,0,0,154,0,0,155,0,0,156,0,0,157,0,0,158,0,0,159,0,0,160,0,0,161,0,0,162,0,0,163,0,0,164,0,0,165,0,0,166,0,0,167,0,0,168,0,0,169,0,0,170,0,0,171,0,0,172,0,0,173,0,16,95,1,4,16,2,4,50,12,4,17,15,4,19,16,4,95,45,4,89,430],[0,0,0,0,0,0,0,0,0,0,0,0,0,0,0,0,0,0,0,0,0,0,0,0,0,0,0,0,0,0,0,0,0,0,0,0,0,0,0,0,0,0,0,0,0,0,0,0,0,0,0,0,0,0,0,0,0,0,0,0,0,0,0,0,0,0,0,0,0,0,0,0,0,0,0,0,0,0,0,0,0,0,0,0,0,0,0,0,0,0,0,0,0,0,0,0,0,0,0,0,0,0,0,0,0,0,0,0,0,0,0,0,0,0,0,0,0,0,0,0,0,0,0,0,0,0,0,0,0,0,0,0,0,0,0,0,0,0,0,0,0,0,0,0,0,0,0,0,0,0,0,0,0,0,0,0,0,0,0,0,0,0,0,0,0,0,0,0,0,0,0,0,0,0,0,0,0,0,0,0,0,0,0,0,0,0,0,0,0,0,0,0,0,0,0,0,0,0,0,0,0,0,0,0,0,0,0,0,0,0,0,0,0,0,0,120],[-1,1,-1,1,-1,1,-1,-1,-1,-1,-1,1,-1,-1,-1,-1,1,-1,-1,-1,-1,1,-1,-1,-1,-1,1,-1,-1,-1,-1,1,-1,-1,-1,-1,1,-1,-1,-1,-1,1,-1,-1,-1,-1,-1,-1,-1,-1,-1,-1,-1,-1,-1,-1,-1,-1,-1,-1,-1,-1,-1,-1,-1,-1,1,-1,1,-1,1,-1,1,-1,-1,1,-1,1,-1,1,5,-1,-1,1,5,-1,-1,1,5,-1,-1,1,5,-1,-1,1,-1,1,-1,1,-1,1,-1,1,-1,1,-1,-1,-1,-1,-1,-1,-1,1,-1,1,-1,1,-1,1,-1,1,-1,-1,-1,-1,-1,-1,1,-1,1,-1,-1,-1,-1,-1,-1,1,-1,1,-1,-1,-1,-1,-1,-1,1,-1,1,-1,-1,-1,-1,-1,-1,1,-1,1,-1,-1,-1,-1,-1,-1,1,-1,1,-1,-1,-1,-1,-1,-1,1,-1,1,-1,-1,-1,-1,-1,-1,1,-1,1,-1,-1,-1,-1,-1,-1,1,-1,1,-1,-1,-1,-1,-1,-1,1,-1,1,-1,-1,-1,-1,-1,-1,1,-1,-1,1,-1,17,1],[0,20,0,21,0,1,0,0,0,0,0,1,0,0,0,0,22,0,0,0,0,23,0,0,0,0,24,0,0,0,0,25,0,0,0,0,26,0,0,0,0,27,0,0,0,0,0,0,0,0,0,0,0,0,0,0,0,0,0,0,0,0,0,0,0,0,6,0,28,0,29,0,30,0,0,7,0,7,0,8,3,3,0,8,3,3,0,9,3,3,0,9,10,10,0,31,0,4,0,5,0,32,0,4,0,5,0,0,0,0,0,0,0,6,0,33,0,4,0,5,0,1,0,0,0,0,0,0,2,0,1,0,0,0,0,0,0,2,0,1,0,0,0,0,0,0,2,0,1,0,0,0,0,0,0,2,0,1,0,0,0,0,0,0,2,0,1,0,0,0,0,0,0,2,0,1,0,0,0,0,0,0,2,0,1,0,0,0,0,0,0,2,0,1,0,0,0,0,0,0,2,0,1,0,0,0,0,0,0,2,0,0,34,35,36,37]],[[{"name":"jkjinrai","rect":[0,0,257,456],"offset":[0,0],"originalSize":[257,456],"capInsets":[0,0,0,0]}],[0],0,[0],[2],[38]],[[{"name":"dbfgmu","rect":[0,0,1920,1080],"offset":[0,0],"originalSize":[1920,1080],"capInsets":[0,0,0,0]}],[0],0,[0],[2],[39]],[[{"name":"default_sprite_splash","rect":[0,0,2,2],"offset":[0,0],"originalSize":[2,2],"capInsets":[0,0,0,0]}],[0],0,[0],[2],[40]],[[{"name":"mhbtuq","rect":[0,0,815,658],"offset":[0,0],"originalSize":[815,658],"capInsets":[0,0,0,0]}],[0],0,[0],[2],[41]],[[{"name":"jyuedcpke","rect":[0,0,131,134],"offset":[0,0],"originalSize":[131,134],"capInsets":[0,0,0,0]}],[0],0,[0],[2],[42]],[[{"name":"jsespydwev","rect":[0,0,95,95],"offset":[0,0],"originalSize":[95,95],"capInsets":[0,0,0,0]}],[0],0,[0],[2],[43]],[[{"name":"cmydbtyirr","rect":[0,0,257,230],"offset":[0,0],"originalSize":[257,230],"capInsets":[0,0,0,0]}],[0],0,[0],[2],[44]],[[{"name":"uvcrbg","rect":[0,0,233,75],"offset":[0,0],"originalSize":[233,75],"capInsets":[24,27,102,31]}],[0],0,[0],[2],[45]],[[{"name":"bmfeai","rect":[0,0,131,134],"offset":[0,0],"originalSize":[131,134],"capInsets":[0,0,0,0]}],[0],0,[0],[2],[46]],[[{"name":"xcoiy","rect":[0,0,33,33],"offset":[0,0],"originalSize":[33,33],"capInsets":[0,0,0,0]}],[0],0,[0],[2],[47]],[[{"name":"idkqiew","rect":[0,0,223,194],"offset":[0,0],"originalSize":[223,194],"capInsets":[0,0,0,0]}],[0],0,[0],[2],[48]],[[{"name":"jlanbsj","rect":[0,0,815,658],"offset":[0,0],"originalSize":[815,658],"capInsets":[0,0,0,0]}],[0],0,[0],[2],[49]],[[{"name":"qscozpvwi","rect":[0,0,257,232],"offset":[0,0],"originalSize":[257,232],"capInsets":[0,0,0,0]}],[0],0,[0],[2],[50]],[[{"name":"xijcvwun","rect":[0,0,1579,879],"offset":[0,0],"originalSize":[1579,879],"capInsets":[0,0,0,0]}],[0],0,[0],[2],[51]],[[{"name":"default_editbox_bg","rect":[0,0,40,40],"offset":[0,0],"originalSize":[40,40],"capInsets":[12,12,12,12]}],[0],0,[0],[2],[52]]]]