[1,["ecpdLyjvZBwrvm+cedCcQy","f0BIwQ8D5Ml7nTNQbh1YlS","29FYIk+N1GYaeWH/q1NxQO","e97GVMl6JHh5Ml5qEDdSGa","4c2OBgGY5OcJhs1I6fEib1","a2MjXRFdtLlYQ5ouAFv/+R","bcQMmx+oRIR4Kg/kV+i0jz","0fvyQF2UxNB4wc5oGDYBTV","48nEOJxHdB8qJvScNVWHNd","83YTutZ/9NRJ4vmbIfBIFz","71VhFCTINJM6/Ky3oX9nBT","7cQ9sMtJpJ55+tth5cagJ7","68dtJIlL1NWruA292YMiGI","e5fNqfDHxGyoD5weSNYMPn","b6UUxLQGJNb4FtVj+q4HxD","a1+/ipOH1NlIQha6Exzfjw","2a9VVfuxxA/Jh3affCg9zq","2fL9YQYf9LorU8garT6Uta","58O2TQSEJAr47HcPguSFP8","74YhnAl4tKTbWErrv77DTA","4bE0YRUu9Oep8bwTU+msse","0bMvVi1nVDQaZ8Fh0R2EFH","bfxL6mwMRMj7tHnhVm/Tjz","f9QJW/jPVAjqYOiTGWPHQl","18ps6lS41BzZu+/pk+aqvd","accILgJ65Oq6XI03Zsx776","c28+D2GfpOgq1o01qOnTAb","ddbMnEuJ1J2b5mp9ezS2bd","39QmNMzQtK/a0Iy9ZbLcVj","93oYxi2+xOYL1swUUGAQsC","cfffhBQNxG/rjyUT9BSAGK","7fKa6PrFRPRIfPQ09Lj8oi","0eLGtZij1Oipj6hePenzvM","2bClG3rtNJh5yLx7hOU4wi","ddYE4LKYxBk6awCnqoA1Ra","08XprgkftMgaIg3lcjpZDz","d2GpyzUCVLAY72GU1rca92","ca/Z2fYMtI5rRNFfGDhyGa","02delMVqdBD70a/HSD99FK","ceWCxBJLRO0pC4Ok8bGH9O","87ThVnX1JG95jL4VCAD+q5","92zgRqy91IqowYejo3Ekio","b4P/PCArtIdIH38t6mlw8Y","e8Ueib+qJEhL6mXAHdnwbi","94/PHul5VGvaJ2eS7+RR0/"],["node","_textureSetter","_spriteFrame","_parent","_N$target","_N$hoverSprite","_N$disabledSprite","_N$pressedSprite","timeLabel","userScoreLabel","playScr","playBtn","musicBtn","soundBtn","timerNode","resultNode","tipNode","userCoinNode","scene","_clip"],[["cc.Node",["_name","_active","_id","_opacity","_components","_contentSize","_parent","_trs","_children","_color","_anchorPoint"],-1,9,5,1,7,2,5,5],"cc.SpriteFrame",["cc.Sprite",["_sizeMode","_enabled","_type","_fillType","_fillRange","node","_materials","_spriteFrame"],-2,1,3,6],["cc.Label",["_string","_N$verticalAlign","_fontSize","_lineHeight","_N$horizontalAlign","_N$overflow","_enableWrapText","_N$cacheMode","node","_materials"],-5,1,3],["cc.Widget",["_alignFlags","_top","_originalWidth","_originalHeight","node","_target"],-1,1,1],["cc.Button",["_N$transition","node","clickEvents","_N$target","_N$pressedColor","_N$disabledColor","_N$hoverSprite","_N$disabledSprite","_N$pressedSprite"],2,1,9,1,5,5,6,6,6],["cc.LabelOutline",["_width","node","_color"],2,1,5],["cc.AudioSource",["_loop","playOnLoad","node","_clip"],1,1,6],["cc.SceneAsset",["_name","asyncLoadAssets"],1],["cc.Node",["_name","_children","_components","_contentSize","_trs"],2,2,12,5,7],["5fa5exMMXFKupMg6i92JxBn",["node","userCoinNode","tipNode","resultNode","timerNode","soundBtn","musicBtn","playBtn","playScr","userScoreLabel","timeLabel","audioResList"],3,1,1,1,1,1,1,1,1,1,1,1,3],["cc.Canvas",["_fitWidth","_fitHeight","node","_designResolution"],1,1,5],["cc.ClickEvent",["_componentId","handler","target"],1,1],["cc.Layout",["_resize","_N$layoutType","node","_layoutSize"],1,1,5],["cc.BlockInputEvents",["node"],3,1],["cc.Scene",["_name","_active","_children","_anchorPoint","_trs"],1,2,5,7],["cc.Camera",["_clearFlags","_depth","node"],1,1],["4dcb5zaxNBCjpdOCCrYs2fV",["node","miniShowNode","puzzleLayout","aniSprite","touchLayer","MaxSpriteFrameList"],3,1,1,1,1,1,3]],[[0,0,6,4,5,7,2],[2,5,6,7,1],[12,0,1,2,3],[2,5,6,1],[0,0,6,8,4,5,7,2],[2,0,5,6,7,2],[0,0,1,6,4,5,7,3],[4,0,4,5,2],[5,0,1,2,4,5,3,8,6,7,2],[3,0,2,3,6,4,1,5,7,8,9,9],[0,0,6,4,5,2],[0,0,6,4,5,10,7,2],[4,0,4,2],[4,0,2,3,4,4],[6,1,1],[0,0,8,4,5,7,2],[0,0,6,8,2],[0,0,3,6,4,9,5,3],[0,0,4,5,7,2],[5,1,2,4,5,3,8,6,7,1],[5,0,1,2,3,2],[14,0,1],[3,0,2,3,1,8,9,5],[3,0,2,3,4,1,8,9,6],[6,0,1,2],[6,0,1,2,2],[8,0,1,3],[0,0,1,8,3],[0,0,2,8,4,5,7,3],[0,0,8,4,7,2],[0,0,1,6,8,4,7,3],[0,0,1,8,4,5,3],[0,0,1,6,8,4,5,7,3],[0,0,1,6,8,4,5,3],[0,0,1,4,5,7,3],[0,0,6,8,7,2],[0,0,6,4,9,5,7,2],[0,0,1,6,8,3],[0,0,6,8,4,5,2],[0,0,1,6,4,5,10,7,3],[9,0,1,2,3,4,2],[4,0,1,4,5,3],[10,0,1,2,3,4,5,6,7,8,9,10,11,1],[7,2,1],[7,0,1,2,3,3],[2,0,5,6,2],[2,1,0,5,6,3],[2,2,3,4,5,6,4],[11,0,1,2,3,3],[5,0,1,2,4,5,3,6,7,2],[13,0,1,2,3,3],[3,0,4,1,8,9,4],[3,0,2,1,5,8,9,5],[3,0,2,3,8,9,4],[15,0,1,2,3,4,3],[16,0,1,2,3],[17,0,1,2,3,4,5,1]],[[[{"name":"whhmmkftj","rect":[0,0,131,134],"offset":[0,0],"originalSize":[131,134],"capInsets":[0,0,0,0]}],[1],0,[0],[1],[8]],[[{"name":"okperndpgz","rect":[0,0,391,155],"offset":[0,0],"originalSize":[391,155],"capInsets":[0,0,0,0]}],[1],0,[0],[1],[9]],[[{"name":"default_btn_disabled","rect":[0,0,40,40],"offset":[0,0],"originalSize":[40,40],"capInsets":[12,12,12,12]}],[1],0,[0],[1],[10]],[[{"name":"flmwsqblrs","rect":[0,0,377,150],"offset":[0,0],"originalSize":[377,150],"capInsets":[0,0,0,0]}],[1],0,[0],[1],[11]],[[{"name":"gfpeza","rect":[0,0,323,141],"offset":[0,0],"originalSize":[323,141],"capInsets":[0,0,0,0]}],[1],0,[0],[1],[12]],[[{"name":"upinn","rect":[0,0,131,134],"offset":[0,0],"originalSize":[131,134],"capInsets":[0,0,0,0]}],[1],0,[0],[1],[13]],[[{"name":"cfndr","rect":[0,0,765,750],"offset":[0,0],"originalSize":[765,750],"capInsets":[0,0,0,0]}],[1],0,[0],[1],[14]],[[[26,"game",null],[15,"gameLayer",[-14,-15,-16],[[12,45,-1],[42,-12,-11,-10,-9,-8,-7,-6,-5,-4,-3,-2,[74,75,76,77,78,79,80,81,82,83]],[43,-13]],[5,1920,1080],[0,0,0,0,0,0,1,1,1,0]],[40,"playNode",[-19,-20,-21,-22,-23,-24,-25],[[[1,-17,[16],17],-18],4,1],[5,1865,1054],[-27.641,2.126,0,0,0,0,1,1,1,1]],[27,"win",false,[-26,-27,-28,-29,-30,-31]],[28,"Canvas","a5esZu+45LA5mBpvttspPD",[-35,1],[[48,true,false,-32,[5,1920,1080]],[12,45,-33],[44,true,true,-34,84]],[5,1920,1080],[960,540,0,0,0,0,1,1,1,1]],[4,"btnStartGame",2,[-39],[[49,1,-37,[[2,"5fa5exMMXFKupMg6i92JxBn","btnEvent",1]],[4,4291348680],[4,3363338360],-36,9,10],[1,-38,[11],12]],[5,377,150],[425.672,-317.571,0,0,0,0,1,1,1,1]],[29,"topNode",[-41,-42,-43,-44],[[7,1,-40,1]],[0,540,0,0,0,0,1,1,1,1]],[30,"timerBar",false,6,[-46,-47,-48],[[41,1,574.982,-45,1]],[1120.945,-574.982,0,0,0,0,1,1,1,1]],[31,"gameResult",false,[-50,3,-51],[[7,45,-49,1]],[5,1920,1080]],[16,"mainNode",1,[2,6,8,-52]],[32,"userCoin",false,6,[-54,-55],[[3,-53,[26]]],[5,215,60],[-378.494,-100.856,0,0,0,0,1,1,1,1]],[0,"musicBtn",6,[[19,-57,[[2,"5fa5exMMXFKupMg6i92JxBn","btnEvent",1]],[4,4291348680],[4,3363338360],-56,32,33,34],[5,2,-58,[35],36]],[5,131,134],[842.547,-85.935,0,0,0,0,1,1,1,1]],[4,"btExit",3,[-62],[[8,1,-60,[[2,"5fa5exMMXFKupMg6i92JxBn","btnEvent",1]],[4,4291348680],[4,3363338360],-59,45,46,47],[1,-61,[48],49]],[5,391,155],[299.653,-375.035,0,0,0,0,1,1,1,1]],[4,"btStartOver",3,[-66],[[8,1,-64,[[2,"5fa5exMMXFKupMg6i92JxBn","btnEvent",1]],[4,4291348680],[4,3363338360],-63,51,52,53],[1,-65,[54],55]],[5,391,155],[-260.948,-375.035,0,0,0,0,1,1,1,1]],[15,"btNextGame",[-70],[[8,1,-68,[[2,"5fa5exMMXFKupMg6i92JxBn","btnEvent",1]],[4,4291348680],[4,3363338360],-67,59,60,61],[1,-69,[62],63]],[5,391,155],[-0.148,-312.822,0,0,0,0,1,1,1,1]],[33,"gameRule",false,9,[-72,-73],[[7,45,-71,1]],[5,1920,1080]],[34,"btnSound",false,[[19,-75,[[2,"5fa5exMMXFKupMg6i92JxBn","btnEvent",1]],[4,4291348680],[4,3363338360],-74,68,69,70],[45,2,-76,[71]]],[5,134,118],[558.067,1008,0,0,0,0,1,1,1,1]],[0,"puzzleLayout",2,[[46,false,2,-77,[6]],[50,1,3,-78,[5,775,760]]],[5,775,760],[-327.828,-3.049,0,0,0,0,1,1,1,1]],[0,"btnReturn",6,[[8,1,-80,[[2,"5fa5exMMXFKupMg6i92JxBn","btnEvent",1]],[4,4291348680],[4,3363338360],-79,27,28,29],[1,-81,[30],31]],[5,131,134],[-839.312,-85.485,0,0,0,0,1,1,1,1]],[17,"mask",91.035,8,[[5,0,-82,[37],38],[13,45,100,100,-83],[21,-84]],[4,4278190080],[5,1920,1080]],[17,"mask",91.035,15,[[5,0,-85,[64],65],[13,45,100,100,-86],[21,-87]],[4,4278190080],[5,1920,1080]],[18,"closeTipBtn",[[3,-88,[66]],[20,3,-90,[[2,"5fa5exMMXFKupMg6i92JxBn","btnEvent",1]],-89]],[5,92,90],[316.819,113.789,0,0,0,0,1,1,1,0]],[4,"bottomNode",1,[16,-92],[[12,44,-91]],[5,1920,0],[0,-540,0,0,0,0,1,1,1,1]],[6,"tipBtn",false,22,[[1,-93,[72],73],[20,3,-95,[[2,"5fa5exMMXFKupMg6i92JxBn","btnEvent",1]],-94]],[5,131,134],[549.923,1008,0,0,0,0,1,1,1,0]],[10,"bg",1,[[5,0,-96,[0],1],[13,45,1920,1080,-97]],[5,1920,1080]],[35,"userScore",2,[-98,-99],[-74.671,460.919,0,0,0,0,1,1,1,1]],[0,"New Label",25,[[51,"SCORE:",1,1,-100,[2]],[24,2,-101]],[5,157.36,54.4],[0,-0.43400000000008276,0,0,0,0,1,1,1,0]],[11,"scoreNum",25,[[22,"99999",50,50,1,-102,[3]]],[5,139.04,63],[0,0,0.5],[106.363,0,0,0,0,0,1,1,1,1]],[0,"miniSprite",2,[[5,0,-103,[4],5]],[5,521,513],[429.554,-29.511,0,0,0,0,1,1,1,1]],[18,"aniSprite",[[3,-104,[7]]],[5,521,513],[183.64,0,0,0,0,0,1,1.1,1.1,1]],[0,"touchuLayer",2,[[7,45,-105,1]],[5,1920,1080],[27.640999999999963,-2.1259999999999764,0,0,0,0,1,1,1,1]],[36,"Label",5,[[9,"PLAY",70,70,false,1,1,1,1,-106,[8]],[25,3,-107,[4,4282754593]]],[4,4282754593],[5,200,70],[0.378,7.307,0,0,0,0,1,1,1,1]],[4,"time",2,[-109],[[1,-108,[14],15]],[5,323,141],[34.5,-464.931,0,0,0,0,1,1,1,1]],[0,"timeNum",32,[[23,"00:00:59",46,46,1,1,-110,[13]]],[5,179.06,57.96],[46.984,-5.45,0,0,0,0,1,1,1,1]],[4,"barBg",7,[-112],[[3,-111,[21]]],[5,86,741],[-209.784,-4.817,0,0,0,0,1,1,1,1]],[11,"coinLable",10,[[52,"10000",48,1,2,-113,[24]],[25,2,-114,[4,4278190080]]],[5,142,50],[0,0,0.5],[-50.685,1,0,0,0,0,1,1,1,1]],[6,"coinIcon",false,3,[[53,"SCORE:",70,70,-115,[42]],[24,2,-116]],[5,272.38,92.2],[-64.743,-160.504,0,0,0,0,1,0.8,0.8,1]],[0,"Label",12,[[9,"Exit Game",50,60,false,1,1,1,1,-117,[44]],[14,-118]],[5,300,60],[0.786,10.481,0,0,0,0,1,1,1,1]],[0,"Label",13,[[9,"Another Game",50,60,false,1,1,1,1,-119,[50]],[14,-120]],[5,500,60],[1.938,8.782,0,0,0,0,1,1,1,1]],[37,"lose",false,8,[-121,14]],[0,"Label",14,[[9,"Restart Game",50,60,false,1,1,1,1,-122,[58]],[14,-123]],[5,500,60],[3.568,9.652,0,0,0,0,1,1,1,1]],[38,"rule",15,[21],[[3,-124,[67]]],[5,885,828]],[54,"New Node",false,[4],[0,0,0],[0,0,0,0,0,0,1,1,1,1]],[10,"Main Camera",4,[[55,7,-1,-125]],[5,960,640]],[16,"aniNode",2,[29]],[56,2,28,17,29,30,[18,19]],[11,"bar",34,[[47,3,1,1,-126,[20]]],[5,72,727],[0,0,0.5],[-38.078,5.285,0,0,0,0,1,1,1,1]],[0,"timeText",7,[[23,"60S",70,70,1,1,-127,[22]]],[5,124.55,88.2],[-222.88,0,0,0,0,0,1,1,1,1]],[10,"iocn",7,[[3,-128,[23]]],[5,120,122]],[6,"gold",false,10,[[3,-129,[25]]],[5,68,71],[-101.801,2.462,0,0,0,0,1,1,1,1]],[6,"winPint",false,3,[[3,-130,[39]]],[5,1039,1872],[0,22.445,0,0,0,0,1,1,1,1]],[0,"title",3,[[1,-131,[40],41]],[5,838,503],[-0.378,128.821,0,0,0,0,1,1,1,1]],[39,"winNum",false,3,[[22,"0",70,70,1,-132,[43]]],[5,38.93,88.2],[0,0,0.5],[62.925,-157.1,0,0,0,0,1,1,1,1]],[0,"title",39,[[1,-133,[56],57]],[5,838,503],[1.362,117.857,0,0,0,0,1,1,1,1]]],0,[0,0,1,0,8,33,0,9,27,0,10,45,0,11,5,0,12,11,0,13,16,0,14,7,0,15,8,0,16,15,0,17,10,0,0,1,0,0,1,0,-1,24,0,-2,9,0,-3,22,0,0,2,0,-2,45,0,-1,25,0,-2,28,0,-3,17,0,-4,44,0,-5,30,0,-6,5,0,-7,32,0,-1,50,0,-2,51,0,-3,36,0,-4,52,0,-5,12,0,-6,13,0,0,4,0,0,4,0,0,4,0,-1,43,0,4,5,0,0,5,0,0,5,0,-1,31,0,0,6,0,-1,7,0,-2,10,0,-3,18,0,-4,11,0,0,7,0,-1,34,0,-2,47,0,-3,48,0,0,8,0,-1,19,0,-3,39,0,-4,15,0,0,10,0,-1,35,0,-2,49,0,4,11,0,0,11,0,0,11,0,4,12,0,0,12,0,0,12,0,-1,37,0,4,13,0,0,13,0,0,13,0,-1,38,0,4,14,0,0,14,0,0,14,0,-1,40,0,0,15,0,-1,20,0,-2,41,0,4,16,0,0,16,0,0,16,0,0,17,0,0,17,0,4,18,0,0,18,0,0,18,0,0,19,0,0,19,0,0,19,0,0,20,0,0,20,0,0,20,0,0,21,0,4,21,0,0,21,0,0,22,0,-2,23,0,0,23,0,4,23,0,0,23,0,0,24,0,0,24,0,-1,26,0,-2,27,0,0,26,0,0,26,0,0,27,0,0,28,0,0,29,0,0,30,0,0,31,0,0,31,0,0,32,0,-1,33,0,0,33,0,0,34,0,-1,46,0,0,35,0,0,35,0,0,36,0,0,36,0,0,37,0,0,37,0,0,38,0,0,38,0,-1,53,0,0,40,0,0,40,0,0,41,0,0,43,0,0,46,0,0,47,0,0,48,0,0,49,0,0,50,0,0,51,0,0,52,0,0,53,0,18,42,1,3,4,2,3,9,3,3,8,4,3,42,6,3,9,8,3,9,14,3,39,16,3,22,21,3,41,29,3,44,133],[0,0,0,0,0,0,0,0,0,0,0,0,0,0,0,0,0,0,0,0,0,0,0,0,0,0,0,0,0,0,0,0,0,0,0,0,0,0,0,0,0,0,0,0,0,0,0,0,0,0,0,0,0,0,0,0,0,0,0,0,0,0,0,0,0,0,0,0,0,0,0,0,0,0,0,0,0,0,0,0,0,0,0,0,0],[-1,2,-1,-1,-1,2,-1,-1,-1,5,6,-1,2,-1,-1,2,-1,2,-1,-2,-1,-1,-1,-1,-1,-1,-1,7,5,6,-1,2,7,5,6,-1,2,-1,2,-1,-1,2,-1,-1,-1,7,5,6,-1,2,-1,7,5,6,-1,2,-1,2,-1,7,5,6,-1,2,-1,2,-1,-1,7,5,6,-1,-1,2,-1,-2,-3,-4,-5,-6,-7,-8,-9,-10,19],[0,15,0,0,0,4,0,0,0,1,2,0,16,0,0,17,0,18,4,19,0,0,0,0,0,0,0,3,1,2,0,20,3,1,2,0,21,0,5,0,0,22,0,0,0,3,1,2,0,6,0,3,1,2,0,6,0,23,0,3,1,2,0,24,0,5,0,0,3,1,2,0,0,25,26,7,27,7,28,29,30,31,32,33,34]],[[{"name":"vjqgq","rect":[0,0,1865,1054],"offset":[0,0],"originalSize":[1865,1054],"capInsets":[0,0,0,0]}],[1],0,[0],[1],[35]],[[{"name":"qixha","rect":[0,0,765,750],"offset":[0,0],"originalSize":[765,750],"capInsets":[0,0,0,0]}],[1],0,[0],[1],[36]],[[{"name":"dbfgmu","rect":[0,0,1920,1080],"offset":[0,0],"originalSize":[1920,1080],"capInsets":[0,0,0,0]}],[1],0,[0],[1],[37]],[[{"name":"default_sprite_splash","rect":[0,0,2,2],"offset":[0,0],"originalSize":[2,2],"capInsets":[0,0,0,0]}],[1],0,[0],[1],[38]],[[{"name":"jyuedcpke","rect":[0,0,131,134],"offset":[0,0],"originalSize":[131,134],"capInsets":[0,0,0,0]}],[1],0,[0],[1],[39]],[[{"name":"nsevf","rect":[0,0,391,155],"offset":[0,0],"originalSize":[391,155],"capInsets":[0,0,0,0]}],[1],0,[0],[1],[40]],[[{"name":"pmdoyc","rect":[0,0,838,503],"offset":[0,0],"originalSize":[838,503],"capInsets":[0,0,0,0]}],[1],0,[0],[1],[41]],[[{"name":"default_btn_pressed","rect":[0,0,40,40],"offset":[0,0],"originalSize":[40,40],"capInsets":[12,12,12,12]}],[1],0,[0],[1],[42]],[[{"name":"default_btn_normal","rect":[0,0,40,40],"offset":[0,0],"originalSize":[40,40],"capInsets":[12,12,12,12]}],[1],0,[0],[1],[43]],[[{"name":"dedbfwhrl","rect":[0,0,838,503],"offset":[0,0],"originalSize":[838,503],"capInsets":[0,0,0,0]}],[1],0,[0],[1],[44]]]]